HeslStudio/__init__.py
HeslStudio/main.py
HeslStudio-1.0.dist-info/METADATA
HeslStudio-1.0.dist-info/WHEEL
HeslStudio-1.0.dist-info/top_level.txt
HeslStudio-1.0.dist-info/RECORD
